ez_chess/__init__.py
ez_chess/cli.py
ez_chess/py.typed
ez_chess/core/__init__.py
ez_chess/core/agent.py
ez_chess/core/board_state.py
ez_chess/core/config.py
ez_chess/core/engine.py
ez_chess/core/pgn_parser.py
ez_chess/tools/__init__.py
ez_chess/ui/__init__.py
ez_chess/ui/main.py
ez_chess-1.0.3.dist-info/licenses/LICENSE
src/__init__.py
src/agent.py
src/async_analysis.py
src/board_state.py
src/chess_fundamentals.py
src/config.py
src/deep_analysis.py
src/engine.py
src/enhanced_explainability.py
src/explainability_service.py
src/explanation_framework.py
src/groq_agent.py
src/llm_prompts.py
src/move_parser.py
src/pgn_parser.py
src/query_understanding.py
src/tool_schemas.py
src/why_engine.py
ui/__init__.py
ui/analysis_panel.py
ui/board.py
ui/chat_panel.py
ui/game_panel.py
ui/main.py
ui/theme.py
ez_chess-1.0.3.dist-info/METADATA
ez_chess-1.0.3.dist-info/WHEEL
ez_chess-1.0.3.dist-info/entry_points.txt
ez_chess-1.0.3.dist-info/top_level.txt
ez_chess-1.0.3.dist-info/RECORD
