Metadata-Version: 2.4
Name: ez-chess
Version: 1.0.3
Summary: AI-Powered Chess Analysis SDK - Combine Stockfish with LLMs for human-readable chess explanations
Author-email: JBAC EdTech <team@jbac.dev>
Maintainer: Anubhav Choudhery, Jai Ansh Bindra
License: MIT License
Project-URL: Homepage, https://github.com/AnubhavChoudhery/EZ-Chess
Project-URL: Documentation, https://github.com/AnubhavChoudhery/EZ-Chess#readme
Project-URL: Repository, https://github.com/AnubhavChoudhery/EZ-Chess.git
Project-URL: Issues, https://github.com/AnubhavChoudhery/EZ-Chess/issues
Project-URL: Changelog, https://github.com/AnubhavChoudhery/EZ-Chess/releases
Keywords: chess,stockfish,ai,llm,analysis,chess-engine,groq,ollama,langchain,chess-analysis,explainable-ai,mcp,model-context-protocol,agentic,ai-agent,langgraph,multi-agent,chess-ai,function-calling
Classifier: Development Status :: 4 - Beta
Classifier: Intended Audience :: Developers
Classifier: Intended Audience :: Education
Classifier: Intended Audience :: End Users/Desktop
Classifier: License :: OSI Approved :: MIT License
Classifier: Operating System :: OS Independent
Classifier: Programming Language :: Python :: 3
Classifier: Programming Language :: Python :: 3.10
Classifier: Programming Language :: Python :: 3.11
Classifier: Programming Language :: Python :: 3.12
Classifier: Topic :: Games/Entertainment :: Board Games
Classifier: Topic :: Scientific/Engineering :: Artificial Intelligence
Classifier: Topic :: Software Development :: Libraries :: Python Modules
Requires-Python: >=3.10
License-File: LICENSE
Requires-Dist: python-chess>=1.999
Requires-Dist: pyyaml>=6.0
Requires-Dist: requests>=2.31.0
Requires-Dist: langchain-core>=0.3.28
Requires-Dist: langgraph>=0.2.60
Requires-Dist: langchain-ollama>=0.2.2
Requires-Dist: langchain-groq>=0.2.0
Requires-Dist: pillow>=11.1.0
Provides-Extra: local
Requires-Dist: langchain-core>=0.3.28; extra == "local"
Requires-Dist: langgraph>=0.2.60; extra == "local"
Requires-Dist: langchain-ollama>=0.2.2; extra == "local"
Provides-Extra: cloud
Requires-Dist: langchain-core>=0.3.28; extra == "cloud"
Requires-Dist: langgraph>=0.2.60; extra == "cloud"
Requires-Dist: langchain-groq>=0.2.0; extra == "cloud"
Provides-Extra: gui
Requires-Dist: pillow>=11.1.0; extra == "gui"
Provides-Extra: all
Requires-Dist: langchain-core>=0.3.28; extra == "all"
Requires-Dist: langgraph>=0.2.60; extra == "all"
Requires-Dist: langchain-ollama>=0.2.2; extra == "all"
Requires-Dist: langchain-groq>=0.2.0; extra == "all"
Requires-Dist: pillow>=11.1.0; extra == "all"
Provides-Extra: dev
Requires-Dist: pytest>=7.0; extra == "dev"
Requires-Dist: pytest-cov>=4.0; extra == "dev"
Requires-Dist: black>=23.0; extra == "dev"
Requires-Dist: mypy>=1.0; extra == "dev"
Requires-Dist: ruff>=0.1.0; extra == "dev"
Dynamic: license-file
